{
	"person": {
		"name": "Adam Marsh",
		"githubUsername": "Adam2Marsh",
		"imageURL": "https://avatars.githubusercontent.com/u/7213334?v=4",
		"bio": "",
		"primary": true
	},
	"plugins": [
		{
			"files": [
				{
					"path": "Travel/gwr-wifi-status.1m.py",
					"filename": "gwr-wifi-status.1m.py",
					"content": "#!/usr/local/bin/python\n# -*- coding: utf-8 -*-\n# \u003cbitbar.title\u003eGWR Wifi Status\u003c/bitbar.title\u003e\n# \u003cbitbar.version\u003ev0.1\u003c/bitbar.version\u003e\n# \u003cbitbar.author\u003eAdam Marsh\u003c/bitbar.author\u003e\n# \u003cbitbar.author.github\u003eAdam2Marsh\u003c/bitbar.author.github\u003e\n# \u003cbitbar.desc\u003eShows the WiFi Status when on a GWR train.\u003c/bitbar.desc\u003e\n# \u003cbitbar.image\u003ehttp://gwr.passengerwifi.com/library/images/logo-gwr%402x.png\u003c/bitbar.image\u003e\n# \u003cbitbar.dependencies\u003eGWR-Wifi,python,dryscrape\u003c/bitbar.dependencies\u003e\n\n# GWR Passenger Wifi Page\nurl = \"http://gwr.passengerwifi.com/connected.php\"\n\nimport dryscrape\nimport re\n# import urllib2\n\ntry:\n    # result = urllib2.urlopen(url, timeout = 5).read()\n    session = dryscrape.Session()\n    session.visit(url)\n    result = session.body();\n    print \"🚂\"\n    print \"---\"\n\n    try:\n        signalStrength = re.search('\u003cdiv class=\\\"guagevalue\\\" id=\\\"signalvalue\\\"\u003e(\\d+%)\u003c\\/div\u003e', result);\n        print \"Signal Strength:\"\n        print signalStrength.group(1) + \"| href=\" + url\n    except:\n        print \"❌\"\n        print \"---\"\n\n    try:\n        howBusy = re.search('\u003cdiv class=\\\"guagevalue\\\"\u003e([\\w\\s]+)\u003c\\/div\u003e', result);\n        print \"How Busy:\"\n        print howBusy.group(1) + \"| href=\" + url\n    except:\n        print \"❌\"\n        print \"---\"\n\n    try:\n        location = re.search('\u003cdiv class=\\\"description\\\"\u003e[\\t\\n\\r]\\s+\u003ch2\u003e([\\w\\s]+)\u003c\\/h2\u003e', result);\n        print \"Location:\"\n        print location.group(1) + \"| href=\" + url\n    except:\n        print \"❌\"\n        print \"---\"\nexcept:\n    print \"❌\"\n    print \"---\"\n    print \"GWR Passenger Wifi Not Available | color=red\"\n    print \"---\"\n"
				}
			],
			"path": "Travel/gwr-wifi-status.1m.py",
			"filename": "gwr-wifi-status.1m.py",
			"dir": "Travel",
			"docsPlugin": "Travel/gwr-wifi-status.1m.py.html",
			"docsCategory": "Travel.html",
			"pathSegments": [
				"Travel"
			],
			"categoryPathSegments": [
				{
					"path": "Travel",
					"text": "Travel",
					"isLast": true
				}
			],
			"title": "GWR Wifi Status",
			"version": "v0.1",
			"author": "Adam Marsh",
			"authors": [
				{
					"name": "Adam Marsh",
					"githubUsername": "Adam2Marsh",
					"imageURL": "https://avatars.githubusercontent.com/u/7213334?v=4",
					"bio": "",
					"primary": true
				}
			],
			"desc": "Shows the WiFi Status when on a GWR train.",
			"imageURL": "http://gwr.passengerwifi.com/library/images/logo-gwr%402x.png",
			"dependencies": [
				"GWR-Wifi",
				"python",
				"dryscrape"
			],
			"aboutURL": "",
			"lastUpdated": "2021-03-08T15:22:08.251763Z",
			"vars": null
		}
	]
}